llama_index/embeddings/huggingface_itrex/__init__.py
llama_index/embeddings/huggingface_itrex/base.py
llama_index_embeddings_itrex-0.4.0.dist-info/METADATA
llama_index_embeddings_itrex-0.4.0.dist-info/WHEEL
llama_index_embeddings_itrex-0.4.0.dist-info/RECORD
