Metadata-Version: 2.1
Name: llama-index-embeddings-itrex
Version: 0.4.0
Summary: llama-index embeddings Intel Extension for Transformers integration
License: MIT
Author: Your Name
Author-email: you@example.com
Requires-Python: >=3.9,<4.0
Classifier: License :: OSI Approved :: MIT License
Classifier: Programming Language :: Python :: 3
Classifier: Programming Language :: Python :: 3.9
Classifier: Programming Language :: Python :: 3.10
Classifier: Programming Language :: Python :: 3.11
Classifier: Programming Language :: Python :: 3.12
Requires-Dist: accelerate (>=0.28.0,<0.29.0)
Requires-Dist: datasets (>=2.18.0,<3.0.0)
Requires-Dist: llama-index-core (>=0.12.0,<0.13.0)
Requires-Dist: llama-index-embeddings-huggingface (>=0.4.0,<0.5.0)
Requires-Dist: onnx (>=1.15.0,<2.0.0)
Requires-Dist: torch (>=2.2.2,<3.0.0)
